{"cameraMode":{"drawMode":0,"name":"Shaded","section":"Shading Mode"},"sceneLighting":true,"audioPlay":false,"sceneViewState":{"m_AlwaysRefresh":false,"showFog":true,"showSkybox":false,"showFlares":true,"showImageEffects":true,"showParticleSystems":true,"showVisualEffectGraphs":true,"m_FxEnabled":true},"in2DMode":false,"pivot":{"x":41.13180160522461,"y":-16.02239227294922,"z":-35.81822204589844},"rotation":{"x":0.5161046981811523,"y":-0.01541511807590723,"z":0.009291482158005238,"w":0.8563306331634522},"size":49.898643493652347,"orthographic":false}